{
  "product": "Ruslan Magana Sports Intelligence",
  "competition": "FIFA World Cup 2026",
  "source": "openfootball",
  "last_updated": "2026-06-28T22:58:48.098832+00:00",
  "region": "Worldwide",
  "matches": [
    {
      "rank": 1,
      "label": "Portugal vs Croatia",
      "stage": "round_of_32",
      "interest_score": 70,
      "hot": true
    },
    {
      "rank": 2,
      "label": "Brazil vs Japan",
      "stage": "round_of_32",
      "interest_score": 69,
      "hot": false
    },
    {
      "rank": 3,
      "label": "Netherlands vs Morocco",
      "stage": "round_of_32",
      "interest_score": 67,
      "hot": false
    },
    {
      "rank": 4,
      "label": "Argentina vs Cape Verde",
      "stage": "round_of_32",
      "interest_score": 66,
      "hot": false
    },
    {
      "rank": 5,
      "label": "France vs Sweden",
      "stage": "round_of_32",
      "interest_score": 65,
      "hot": false
    }
  ]
}
