{
  "product": "Ruslan Magana Sports Intelligence",
  "competition": "FIFA World Cup 2026",
  "source": "openfootball+thestatsapi",
  "last_updated": "2026-07-08T01:55:03.650161+00:00",
  "region": "Worldwide",
  "matches": [
    {
      "rank": 1,
      "label": "Spain vs Belgium",
      "stage": "quarterfinals",
      "interest_score": 80,
      "hot": true
    },
    {
      "rank": 2,
      "label": "France vs Morocco",
      "stage": "quarterfinals",
      "interest_score": 78,
      "hot": false
    },
    {
      "rank": 3,
      "label": "Norway vs England",
      "stage": "quarterfinals",
      "interest_score": 70,
      "hot": false
    }
  ]
}
